MySerializers/json/__init__.py
MySerializers/json/json_serializer.py
MySerializers/json/parser.py
MySerializers/src/__init__.py
MySerializers/src/constants.py
MySerializers/src/serializer.py
MySerializers/toml/__init__.py
MySerializers/toml/parser.py
MySerializers/toml/toml_serializer.py
MySerializers/yaml/__init__.py
MySerializers/yaml/yaml_serializer.py
MySerializers-1.2.dist-info/METADATA
MySerializers-1.2.dist-info/WHEEL
MySerializers-1.2.dist-info/top_level.txt
MySerializers-1.2.dist-info/RECORD
